qt_build_utils/__init__.py
qt_build_utils/__main__.py
qt_build_utils/convert.py
qt_build_utils/main.py
qt_build_utils/path_manager.py
qt_build_utils-1.0.6.dist-info/METADATA
qt_build_utils-1.0.6.dist-info/WHEEL
qt_build_utils-1.0.6.dist-info/entry_points.txt
qt_build_utils-1.0.6.dist-info/RECORD
