Metadata-Version: 2.4
Name: qt-build-utils
Version: 1.0.6
Summary: An utility to facilitate the building of Qt based projects
Requires-Python: >=3.10
Requires-Dist: click>=8.1.8
Requires-Dist: setuptools>=75.8.2
